netapi/__init__.py
netapi/connector/__init__.py
netapi/connector/device.py
netapi/connector/eos/__init__.py
netapi/connector/eos/pyeapier.py
netapi/connector/linux/__init__.py
netapi/connector/linux/paramikoer.py
netapi/connector/linux/subprocesser.py
netapi/metadata.py
netapi/net/__init__.py
netapi/net/eos/__init__.py
netapi/net/eos/pyeapier.py
netapi/net/facts.py
netapi/net/interface.py
netapi/net/route.py
netapi/net/vlan.py
netapi/net/vrrp.py
netapi/probe/__init__.py
netapi/probe/eos/__init__.py
netapi/probe/eos/pyeapier.py
netapi/probe/ios/__init__.py
netapi/probe/ios/netmikoer.py
netapi/probe/junos/__init__.py
netapi/probe/junos/pyezer.py
netapi/probe/linux/__init__.py
netapi/probe/linux/paramikoer.py
netapi/probe/linux/subprocesser.py
netapi/probe/nxos/__init__.py
netapi/probe/nxos/nxapier.py
netapi/probe/ping.py
netapi/probe/utils.py
netapi/probe/xe/__init__.py
netapi/probe/xe/netmikoer.py
netapi/probe/xr/__init__.py
netapi/probe/xr/netmikoer.py
netapi/units.py
netapi-0.2.1.dist-info/WHEEL
netapi-0.2.1.dist-info/METADATA
netapi-0.2.1.dist-info/RECORD
