Metadata-Version: 2.1
Name: netapi
Version: 0.2.1
Summary: Network API library. A programmatic interface to network devices
Home-page: https://gitlab.com/the-networkers/netaudithor/netapi
License: MIT
Keywords: network,library
Author: David Flores
Author-email: davidflores7_8@hotmail.com
Requires-Python: >=3.7,<4.0
Classifier: License :: OSI Approved :: MIT License
Classifier: Programming Language :: Python :: 3
Classifier: Programming Language :: Python :: 3.7
Requires-Dist: bitmath (>=1.3,<2.0)
Requires-Dist: netaddr (>=0.7.19,<0.8.0)
Requires-Dist: pendulum (>=2.0,<3.0)
Requires-Dist: pydantic (>=0.26.0,<0.27.0)
Requires-Dist: pyeapi (>=0.8.2,<0.9.0)
Requires-Dist: pyyaml (>=5.1,<6.0)
Project-URL: Repository, https://gitlab.com/the-networkers/netaudithor/netapi
